stochopy/VERSION
stochopy/__about__.py
stochopy/__init__.py
stochopy/_common.py
stochopy/factory/__init__.py
stochopy/factory/benchmark.py
stochopy/optimize/__init__.py
stochopy/optimize/_common.py
stochopy/optimize/_helpers.py
stochopy/optimize/cmaes/__init__.py
stochopy/optimize/cmaes/_cmaes.py
stochopy/optimize/cmaes/_constraints.py
stochopy/optimize/cpso/__init__.py
stochopy/optimize/cpso/_constraints.py
stochopy/optimize/cpso/_cpso.py
stochopy/optimize/de/__init__.py
stochopy/optimize/de/_constraints.py
stochopy/optimize/de/_de.py
stochopy/optimize/de/_strategy.py
stochopy/optimize/na/__init__.py
stochopy/optimize/na/_na.py
stochopy/optimize/pso/__init__.py
stochopy/optimize/pso/_pso.py
stochopy/optimize/vdcma/__init__.py
stochopy/optimize/vdcma/_vdcma.py
stochopy/sample/__init__.py
stochopy/sample/_common.py
stochopy/sample/_helpers.py
stochopy/sample/hmc/__init__.py
stochopy/sample/hmc/_hmc.py
stochopy/sample/mcmc/__init__.py
stochopy/sample/mcmc/_mcmc.py
stochopy-2.3.0.dist-info/LICENSE
stochopy-2.3.0.dist-info/METADATA
stochopy-2.3.0.dist-info/WHEEL
stochopy-2.3.0.dist-info/top_level.txt
stochopy-2.3.0.dist-info/RECORD
