Metadata-Version: 2.1
Name: stochopy
Version: 2.3.0
Summary: Python library for stochastic numerical optimization
Home-page: https://github.com/keurfonluu/stochopy
Author: Keurfon Luu
License: BSD 3-Clause License
Project-URL: Code, https://github.com/keurfonluu/stochopy
Project-URL: Issues, https://github.com/keurfonluu/stochopy/issues
Platform: any
Classifier: License :: OSI Approved :: BSD License
Classifier: Operating System :: OS Independent
Classifier: Development Status :: 5 - Production/Stable
Classifier: Programming Language :: Python :: 3.7
Classifier: Programming Language :: Python :: 3.8
Classifier: Programming Language :: Python :: 3.9
Classifier: Programming Language :: Python :: 3.10
Classifier: Programming Language :: Python :: 3.11
Requires-Python: >=3.7
License-File: LICENSE
Requires-Dist: importlib-metadata
Requires-Dist: numpy
Requires-Dist: joblib (>=0.12)
